pylore/__init__.py
pylore/blackbox.py
pylore/distances.py
pylore/genetics.py
pylore/lore.py
pylore/treeutils.py
pylore-0.0.2.dist-info/LICENSE.txt
pylore-0.0.2.dist-info/METADATA
pylore-0.0.2.dist-info/WHEEL
pylore-0.0.2.dist-info/top_level.txt
pylore-0.0.2.dist-info/RECORD
